setup.cfg
setup.py
nctu_oauth/__init__.py
nctu_oauth/oauth.py
tornado_NCTU_OAuth.egg-info/PKG-INFO
tornado_NCTU_OAuth.egg-info/SOURCES.txt
tornado_NCTU_OAuth.egg-info/dependency_links.txt
tornado_NCTU_OAuth.egg-info/requires.txt
tornado_NCTU_OAuth.egg-info/top_level.txt
tornado_NCTU_OAuth.egg-info/zip-safe