Metadata-Version: 1.0
Name: tornado-NCTU-OAuth
Version: 0.1.2
Summary: adds NCTU-OAuth support to tornado
Home-page: https://github.com/allenwhale/NCTU-OAuth
Author: allenwhale
Author-email: allencat850502@gmail.com
License: BSD
Keywords: python tornado nctu oauth nctu-oauth
Platform: UNKNOWN
